boosting_cv_llm_sentiment/__init__.py
boosting_cv_llm_sentiment/cli.py
boosting_cv_llm_sentiment/config.py
boosting_cv_llm_sentiment/emoboostllm.py
boosting_cv_llm_sentiment/cv_module/__init__.py
boosting_cv_llm_sentiment/cv_module/emotion_recognition.py
boosting_cv_llm_sentiment/llm_module/__init__.py
boosting_cv_llm_sentiment/llm_module/conversation_manager.py
boosting_cv_llm_sentiment-0.1.1.dist-info/AUTHORS.rst
boosting_cv_llm_sentiment-0.1.1.dist-info/LICENSE
boosting_cv_llm_sentiment-0.1.1.dist-info/METADATA
boosting_cv_llm_sentiment-0.1.1.dist-info/WHEEL
boosting_cv_llm_sentiment-0.1.1.dist-info/entry_points.txt
boosting_cv_llm_sentiment-0.1.1.dist-info/top_level.txt
boosting_cv_llm_sentiment-0.1.1.dist-info/RECORD
