Metadata-Version: 2.1
Name: boosting-cv-llm-sentiment
Version: 0.1.1
Summary: A Python library enhancing conversational AI with emotion detection, using computer vision and NLP. It tags emotions from facial expressions in real-time and integrates them with a Large Language Model for empathetic responses.
Home-page: https://github.com/ToroData/boosting_cv_llm_sentiment
Author: Ricard Santiago Raigada García
Author-email: ricard.raigada@ieee.org
License: Apache Software License
Keywords: boosting_cv_llm_sentiment
Platform: UNKNOWN
Classifier: Development Status :: 2 - Pre-Alpha
Classifier: Intended Audience :: Developers
Classifier: License :: OSI Approved :: Apache Software License
Classifier: Natural Language :: English
Classifier: Programming Language :: Python :: 3
Classifier: Programming Language :: Python :: 3.6
Classifier: Programming Language :: Python :: 3.7
Classifier: Programming Language :: Python :: 3.8
Requires-Python: >=3.6
License-File: LICENSE
License-File: AUTHORS.rst
Requires-Dist: requests
Requires-Dist: numpy (==1.24.3)
Requires-Dist: openai (==1.14.3)
Requires-Dist: opencv-python (==4.5.5.64)
Requires-Dist: Pillow (==10.2.0)
Requires-Dist: pytest (==6.2.4)
Requires-Dist: setuptools (==58.0.4)
Requires-Dist: transformers (==4.34.1)
Requires-Dist: torch
Requires-Dist: torchvision
